image_section_splitter/__init__.py
image_section_splitter/splitter.py
image_section_splitter-1.0.0.dist-info/METADATA
image_section_splitter-1.0.0.dist-info/WHEEL
image_section_splitter-1.0.0.dist-info/RECORD
