Metadata-Version: 2.4
Name: image-section-splitter
Version: 1.0.0
Summary: 세로로 긴 상세페이지 이미지를 시각적 경계 기준으로 안전하게 섹션 분리
Project-URL: Homepage, https://github.com/gandol2/image-section-splitter
Project-URL: Repository, https://github.com/gandol2/image-section-splitter
Project-URL: Documentation, https://github.com/gandol2/image-section-splitter#readme
Author-email: gandol2 <sskim2333@gmail.com>
License: MIT
Keywords: computer-vision,image,opencv,section,split
Classifier: Development Status :: 4 - Beta
Classifier: Intended Audience :: Developers
Classifier: License :: OSI Approved :: MIT License
Classifier: Programming Language :: Python :: 3
Classifier: Programming Language :: Python :: 3.8
Classifier: Programming Language :: Python :: 3.9
Classifier: Programming Language :: Python :: 3.10
Classifier: Programming Language :: Python :: 3.11
Classifier: Programming Language :: Python :: 3.12
Requires-Python: >=3.13
Requires-Dist: matplotlib>=3.10.7
Requires-Dist: opencv-python>=4.12.0.88
Requires-Dist: pandas>=2.3.3
Requires-Dist: scipy>=1.16.2
Provides-Extra: dev
Requires-Dist: black>=22.0.0; extra == 'dev'
Requires-Dist: pytest>=7.0.0; extra == 'dev'
Requires-Dist: ruff>=0.1.0; extra == 'dev'
